nio_cli/__init__.py
nio_cli/cli.py
nio_cli/utils.py
nio_cli/commands/__init__.py
nio_cli/commands/add.py
nio_cli/commands/add_user.py
nio_cli/commands/base.py
nio_cli/commands/blockcheck.py
nio_cli/commands/build.py
nio_cli/commands/buildreadme.py
nio_cli/commands/buildrelease.py
nio_cli/commands/buildspec.py
nio_cli/commands/cfg.py
nio_cli/commands/clone.py
nio_cli/commands/co.py
nio_cli/commands/command.py
nio_cli/commands/config.py
nio_cli/commands/list.py
nio_cli/commands/ln.py
nio_cli/commands/ls.py
nio_cli/commands/new.py
nio_cli/commands/newblock.py
nio_cli/commands/publishblock.py
nio_cli/commands/remove_user.py
nio_cli/commands/server.py
nio_cli/commands/shutdown.py
nio_cli/commands/update.py
nio_cli/utils/__init__.py
nio_cli/utils/files.py
nio_cli/utils/inputs.py
nio_cli/utils/project.py
nio_cli/utils/spec.py
nio_cli/utils/ssl.py
nio_cli/utils/users.py
nio_cli-1.3.1.dist-info/DESCRIPTION.rst
nio_cli-1.3.1.dist-info/METADATA
nio_cli-1.3.1.dist-info/RECORD
nio_cli-1.3.1.dist-info/WHEEL
nio_cli-1.3.1.dist-info/entry_points.txt
nio_cli-1.3.1.dist-info/metadata.json
nio_cli-1.3.1.dist-info/top_level.txt
