Metadata-Version: 2.0
Name: nio-cli
Version: 1.3.1
Summary: Command line tools for the nio Platform
Home-page: https://github.com/niolabs/nio-cli
Author: niolabs
Author-email: support@n.io
License: Apache 2.0
Keywords: nio
Platform: UNKNOWN
Classifier: License :: OSI Approved :: Apache Software License
Requires-Dist: nio
Requires-Dist: requests
Requires-Dist: docopts
Requires-Dist: pycodestyle
Requires-Dist: bcrypt
Requires-Dist: cryptography
Provides-Extra: dev
Requires-Dist: responses; extra == 'dev'
